README
setup.py
ship
ship_readonly
Mothership.egg-info/PKG-INFO
Mothership.egg-info/SOURCES.txt
Mothership.egg-info/dependency_links.txt
Mothership.egg-info/top_level.txt
mothership/__init__.py
mothership/cobbler/__init__.py
mothership/configure/__init__.py
mothership/dns/__init__.py
mothership/ec2/__init__.py
mothership/idrac6/__init__.py
mothership/kv/__init__.py
mothership/ldap/__init__.py
mothership/list_servers/__init__.py
mothership/list_values/__init__.py
mothership/mgmt_vlan/__init__.py
mothership/mothership_models/__init__.py
mothership/network_mapper/__init__.py
mothership/puppet/__init__.py
mothership/serverinfo/__init__.py
mothership/snmp/__init__.py
mothership/ssh/__init__.py
mothership/transkey/__init__.py
mothership/users/__init__.py
mothership/validate/__init__.py
mothership/xen/XenAPI.py
mothership/xen/__init__.py
mothership/zabbix/__init__.py
mothership/zenoss/__init__.py