Metadata-Version: 1.0
Name: Mothership
Version: 0.0.35
Summary: Mothership - asset managment
Home-page: http://mothership.sf.net
Author: Gilt SA team
Author-email: sa@gilt.com
License: UNKNOWN
Platform: UNKNOWN
